policy_sentry/__init__.py
policy_sentry/py.typed
policy_sentry/analysis/__init__.py
policy_sentry/analysis/analyze.py
policy_sentry/analysis/expand.py
policy_sentry/bin/__init__.py
policy_sentry/bin/cli.py
policy_sentry/bin/version.py
policy_sentry/command/__init__.py
policy_sentry/command/create_template.py
policy_sentry/command/initialize.py
policy_sentry/command/query.py
policy_sentry/command/write_policy.py
policy_sentry/querying/__init__.py
policy_sentry/querying/actions.py
policy_sentry/querying/all.py
policy_sentry/querying/arns.py
policy_sentry/querying/conditions.py
policy_sentry/querying/services.py
policy_sentry/shared/__init__.py
policy_sentry/shared/awsdocs.py
policy_sentry/shared/constants.py
policy_sentry/shared/iam_data.py
policy_sentry/shared/data/access-level-overrides.yml
policy_sentry/shared/data/iam-definition.json
policy_sentry/shared/data/overrides-resource-policies.yml
policy_sentry/shared/data/audit/credentials-exposure.txt
policy_sentry/shared/data/audit/privilege-escalation.txt
policy_sentry/shared/data/audit/resource-exposure.txt
policy_sentry/shared/data/audit/resource-policies.txt
policy_sentry/util/__init__.py
policy_sentry/util/access_levels.py
policy_sentry/util/actions.py
policy_sentry/util/arns.py
policy_sentry/util/conditions.py
policy_sentry/util/file.py
policy_sentry/util/policy_files.py
policy_sentry/util/text.py
policy_sentry/writing/__init__.py
policy_sentry/writing/minimize.py
policy_sentry/writing/sid_group.py
policy_sentry/writing/template.py
policy_sentry/writing/validate.py
policy_sentry-0.14.1.dist-info/licenses/LICENSE
policy_sentry-0.14.1.dist-info/METADATA
policy_sentry-0.14.1.dist-info/WHEEL
policy_sentry-0.14.1.dist-info/entry_points.txt
policy_sentry-0.14.1.dist-info/top_level.txt
policy_sentry-0.14.1.dist-info/zip-safe
policy_sentry-0.14.1.dist-info/RECORD
